Metadata-Version: 2.1
Name: moe_peft
Version: 2.0.2
Summary: An Efficient LLM Fine-Tuning Factory Optimized for MoE PEFT
Project-URL: Homepage, https://github.com/TUDB-Labs/MoE-PEFT
Project-URL: Bug Tracker, https://github.com/TUDB-Labs/MoE-PEFT/issues
Classifier: Programming Language :: Python :: 3
Classifier: License :: OSI Approved :: Apache Software License
Classifier: Operating System :: OS Independent
Requires-Python: >=3.8
License-File: LICENSE
Requires-Dist: torch<2.6.0,>=2.4.0
Requires-Dist: datasets
Requires-Dist: evaluate
Requires-Dist: accelerate
Requires-Dist: transformers<4.47.0,>=4.44.0
Requires-Dist: sentencepiece
Requires-Dist: huggingface_hub
Requires-Dist: scikit-learn
Requires-Dist: tiktoken
